fa_icons
i3_workspace_names_daemon
