Metadata-Version: 1.0
Name: i3-workspace-names-daemon
Version: 0.8.0
Summary: Dynamically update the name of each i3wm workspace using font-awesome icons or the names of applications running in each workspace.
Home-page: https://github.com/cboddy/i3-workspace-names-daemon
Author: Chris Boddy
Author-email: chris@boddy.im
License: MIT
Platform: UNKNOWN
